odoo/addons/account_move_cancel_confirm/README.rst
odoo/addons/account_move_cancel_confirm/__init__.py
odoo/addons/account_move_cancel_confirm/__manifest__.py
odoo/addons/account_move_cancel_confirm/i18n/account_move_cancel_confirm.pot
odoo/addons/account_move_cancel_confirm/i18n/it.po
odoo/addons/account_move_cancel_confirm/model/__init__.py
odoo/addons/account_move_cancel_confirm/model/account_move.py
odoo/addons/account_move_cancel_confirm/model/account_payment.py
odoo/addons/account_move_cancel_confirm/readme/CONTRIBUTORS.md
odoo/addons/account_move_cancel_confirm/readme/DESCRIPTION.md
odoo/addons/account_move_cancel_confirm/static/description/icon.png
odoo/addons/account_move_cancel_confirm/static/description/index.html
odoo/addons/account_move_cancel_confirm/tests/__init__.py
odoo/addons/account_move_cancel_confirm/tests/test_account_move_cancel_confirm.py
odoo_addon_account_move_cancel_confirm-18.0.1.0.1.dist-info/METADATA
odoo_addon_account_move_cancel_confirm-18.0.1.0.1.dist-info/WHEEL
odoo_addon_account_move_cancel_confirm-18.0.1.0.1.dist-info/top_level.txt
odoo_addon_account_move_cancel_confirm-18.0.1.0.1.dist-info/RECORD
