Metadata-Version: 2.1
Name: odoo-addon-account_move_cancel_confirm
Version: 18.0.1.0.1
Requires-Python: >=3.10
Requires-Dist: odoo-addon-base_cancel_confirm==18.0.*
Requires-Dist: odoo==18.0.*
Summary: Account Move Cancel Confirm
Home-page: https://github.com/OCA/account-invoicing
License: AGPL-3
Author: Ecosoft, Odoo Community Association (OCA)
Author-email: support@odoo-community.org
Classifier: Programming Language :: Python
Classifier: Framework :: Odoo
Classifier: Framework :: Odoo :: 18.0
Classifier: License :: OSI Approved :: GNU Affero General Public License v3
